assessment_varun/dataset_task.ipynb
assessment_varun/pyproject.toml
assessment_varun/spryfox_script.py
assessment_varun-0.1.0.dist-info/WHEEL
assessment_varun-0.1.0.dist-info/METADATA
assessment_varun-0.1.0.dist-info/RECORD
